cloudflyer/__init__.py
cloudflyer/__main__.py
cloudflyer/bypasser.py
cloudflyer/instance.py
cloudflyer/log.py
cloudflyer/mitm.py
cloudflyer/pool.py
cloudflyer/proxy.py
cloudflyer/server.py
cloudflyer/utils.py
cloudflyer/wssocks.py
cloudflyer/html/CloudFlyer.html
cloudflyer/html/CloudflareChallenge.html
cloudflyer/html/RecaptchaInvisible.html
cloudflyer/html/Turnstile.html
cloudflyer/html/__init__.py
cloudflyer-1.0.5.dist-info/licenses/LICENSE
cloudflyer-1.0.5.dist-info/METADATA
cloudflyer-1.0.5.dist-info/WHEEL
cloudflyer-1.0.5.dist-info/entry_points.txt
cloudflyer-1.0.5.dist-info/top_level.txt
cloudflyer-1.0.5.dist-info/RECORD
