Metadata-Version: 2.4
Name: cloudflyer
Version: 1.0.5
Summary: A Cloudflare/Turnstile captcha bypass API server.
Author-email: jackzzs <jackzzs@outlook.com>
License:                     GNU GENERAL PUBLIC LICENSE
Project-URL: Homepage, https://github.com/zetxtech/cloudflyer
Keywords: python,recaptcha,solver,cloudflare,bypass,cloudflare-bypass,cloudflare-bypass-script,cloudflare-bypasser,drissionpage
Classifier: Development Status :: 4 - Beta
Classifier: Environment :: Console
Classifier: Intended Audience :: Developers
Classifier: Operating System :: MacOS
Classifier: Operating System :: POSIX
Classifier: Operating System :: Microsoft :: Windows
Classifier: License :: OSI Approved :: GNU General Public License v3 (GPLv3)
Classifier: Programming Language :: Python :: 3
Classifier: Programming Language :: Python :: 3 :: Only
Classifier: Programming Language :: Python :: 3.10
Classifier: Programming Language :: Python :: 3.11
Classifier: Programming Language :: Python :: 3.12
Classifier: Programming Language :: Python :: 3.13
Classifier: Programming Language :: Python :: Implementation :: CPython
Requires-Python: >=3.10
License-File: LICENSE
Requires-Dist: fastapi
Requires-Dist: pydantic==2.7.4
Requires-Dist: uvicorn
Requires-Dist: PyVirtualDisplay
Requires-Dist: DrissionPage==4.0.5.6
Requires-Dist: mitmproxy==11.0.2
Requires-Dist: pproxy==2.7.9
Requires-Dist: cachetools
Requires-Dist: loguru
Dynamic: license-file
